README.md
setup.py
opcua_modeler.egg-info/PKG-INFO
opcua_modeler.egg-info/SOURCES.txt
opcua_modeler.egg-info/dependency_links.txt
opcua_modeler.egg-info/entry_points.txt
opcua_modeler.egg-info/requires.txt
opcua_modeler.egg-info/top_level.txt
uamodeler/model_manager.py
uamodeler/namespace_widget.py
uamodeler/refnodesets_widget.py
uamodeler/server_manager.py
uamodeler/uamodeler.py
uamodeler/uamodeler_ui.py