Metadata-Version: 1.0
Name: opcua-modeler
Version: 0.5.14
Summary: OPC-UA Address Space Modeler
Home-page: https://github.com/FreeOpcUa/opcua-modeler
Author: Olivier R-D et al.
Author-email: UNKNOWN
License: GNU General Public License
Platform: UNKNOWN
